azure_helpers/__init__.py
azure_helpers/clients/__init__.py
azure_helpers/clients/cli_client.py
azure_helpers/clients/interface.py
azure_helpers/clients/managed_identity_client.py
azure_helpers/compute/__init__.py
azure_helpers/compute/vmss/__init__.py
azure_helpers/compute/vmss/_create_helper.py
azure_helpers/compute/vmss/vmss.py
azure_helpers-0.0.3.dist-info/LICENSE
azure_helpers-0.0.3.dist-info/METADATA
azure_helpers-0.0.3.dist-info/WHEEL
azure_helpers-0.0.3.dist-info/top_level.txt
azure_helpers-0.0.3.dist-info/RECORD
