Metadata-Version: 2.1
Name: azure-helpers
Version: 0.0.3
Summary: A package which uses azure SDK for creating simple resources and managing them.
Home-page: https://github.com/msanath/azure-helpers.git
Author: Sanath Manavarte
Author-email: msanath@gmail.com
License: UNKNOWN
Platform: UNKNOWN
Classifier: Programming Language :: Python :: 3
Classifier: License :: OSI Approved :: MIT License
Classifier: Operating System :: OS Independent
Requires-Python: >=3.6
Requires-Dist: azure-cli-core
Requires-Dist: azure-mgmt-compute (==13.0.0)
